Metadata-Version: 1.1
Name: list-property
Version: 0.0.1
Summary: Library for lists indexes having associated names like namedtuple and property. Includes list_property and namedlist functions.
Home-page: https://github.com/justengel/list_property
Author: Justin Engel
Author-email: jtengel08@gmail.com
License: MIT
Download-URL: https://github.com/justengel/list_property/archive/v0.0.1.tar.gz
Keywords: list,property,namedlist
Platform: any
Classifier: Programming Language :: Python
Classifier: Programming Language :: Python :: 3
Classifier: Operating System :: OS Independent
